[{"src": [["According", "to", "the", "theory", "of", "evolution", "it", "makes", "more", "sense", "that", "the", "egg", "preceded", "the", "chicken"], ["Before", "the", "chicken", "there", "was", "a", "similar", "but", "different", "creature", "."], ["Let", "'s", "call", "it", "X", "."], ["Its", "completely", "arbitrary", "when", "the", "X", "officially", "evolved", "into", "a", "chicken"], ["at", "some", "point", "it", "does"], ["An", "X", ",", "not", "a", "chicken", "lays", "the", "first", "chicken", "egg", "."], ["The", "chicken", "egg", "comes", "before", "any", "creature", "considered", "a", "chicken", "exist", "."]], "tgt": [["The", "chicken", "egg", "comes", "before", "any", "creature", "considered", "a", "chicken", "exist", "."]]}, {"src": [["According", "to", "the", "theory", "of", "evolution", "it", "makes", "more", "sense", "that", "the", "egg", "preceded", "the", "chicken"], ["Before", "the", "chicken", "there", "was", "a", "similar", "but", "different", "creature", "."], ["Let", "'s", "call", "it", "X", "."], ["Its", "completely", "arbitrary", "when", "the", "X", "officially", "evolved", "into", "a", "chicken"], ["at", "some", "point", "it", "does"], ["An", "X", ",", "not", "a", "chicken", "lays", "the", "first", "chicken", "egg", "."], ["The", "chicken", "egg", "comes", "before", "any", "creature", "considered", "a", "chicken", "exist", "."]], "tgt": [["The", "chicken", "egg", "comes", "before", "any", "creature", "considered", "a", "chicken", "exist", "."]]}, {"src": [["I", "would", "define", "patriotism", "quite", "simply", "as", "supporting", "one", "'s", "country", ",", "but", "not", "*necessarily*", "disparaging", "others", "."], ["Therefore", "I", "would", "say", "that", "the", "antithesis", "of", "patriotism", "is", "not", "having", "a", "global", "perspective", ",", "but", "is", "in", "fact", "selfishness"], ["Someone", "who", "attempts", "to", "extract", "gain", "for", "themselves", "at", "harm", "to", "their", "overall", "country", "is", "acting", "unpatriotically"], ["someone", "who", "assists", "another", "country", "that", "is", "in", "worse", "shape", "instead", "of", "assisting", "their", "own", "can", "still", "be", "a", "patriot", ",", "but", "also", "recognize", "significant", "need", "in", "other", "nations", "and", "decide", "to", "assist", "them", "as", "well"], ["Whether", "you", "support", "immigration", "or", "not", ",", "so", "long", "as", "you", "are", "supporting", "what", "you", "believe", "is", "best", "for", "your", "nation", ",", "you", "are", "still", "acting", "patriotically"], ["even", "if", "you", "decide", "to", "support", "another", "nation", "you", "can", "still", "be", "acting", "patriotically", "as", "well", "so", "long", "as", "you", "support", "your", "nation", "too"]], "tgt": [["Whether", "you", "support", "immigration", "or", "not", ",", "so", "long", "as", "you", "are", "supporting", "what", "you", "believe", "is", "best", "for", "your", "nation", ",", "you", "are", "still", "acting", "patriotically"], ["even", "if", "you", "decide", "to", "support", "another", "nation", "you", "can", "still", "be", "acting", "patriotically", "as", "well", "so", "long", "as", "you", "support", "your", "nation", "too"]]}, {"src": [["American", "patriots", "have", "a", "general", "mentality", "against", "immigration", "."], ["Saying", "these", "people", "shouldn", "\u2019", "t", "be", "allowed", "to", "become", "part", "of", "the", "country", ",", "is", "the", "same", "as", "saying", "they", "are", "worse", ","], ["because", "they", "were", "born", "on", "a", "different", "side", "of", "a", "line"], ["americans", "are", "better", "because", "of", "the", "side", "of", "the", "line", "they", "are", "born", "on"], ["This", "is", "prominent", "in", "many", "ads", "and", "political", "champagnes", ",", "namely", "the", "slogan", "\u201c", "Creating", "jobs", "for", "americans", "\u201d", "."], ["I", "understand", "why", "politics", "use", "this", "slogan"], ["because", "they", "are", "trying", "to", "get", "americans", "to", "vote", "for", "them"], ["this", "slogan", "is", "also", "prominent", "in", "ads", "made", "by", "private", "corporations"], ["As", "if", "creating", "jobs", "for", "americans", "is", "morally", "superior", "to", "creating", "jobs", "for", "people", "of", "other", "countries", "."], ["The", "companies", "launching", "these", "ads", "may", "be", "trying", "to", "win", "in", "the", "american", "market", ",", "so", "they", "can", "sell", "more", "of", "their", "product", ","], ["the", "fact", "that", "this", "can", "increase", "sales", "shows", "that", "many", "americans", "hold", "the", "being", "born", "on", "one", "side", "of", "a", "line", "belief"], ["I", "am", "not", "blaming", "the", "politicians", "or", "corporations", "running", "ads", "running", "these", "slogans"], ["they", "are", "merely", "trying", "to", "win", "votes", "or", "make", "money", "from", "this", "mentality"], ["really", "it", "is", "the", "citizens", "that", "have", "the", "belief", "that", "they", "are", "better", ",", "because", "of", "the", "side", "of", "a", "line", "they", "are", "born", "on", ",", "that", "are", "at", "fault"], ["Patriotism", "is", "really", "just", "this", "belief", "."]], "tgt": [["American", "patriots", "have", "a", "general", "mentality", "against", "immigration", "."], ["Saying", "these", "people", "shouldn", "\u2019", "t", "be", "allowed", "to", "become", "part", "of", "the", "country", ",", "is", "the", "same", "as", "saying", "they", "are", "worse", ","], ["really", "it", "is", "the", "citizens", "that", "have", "the", "belief", "that", "they", "are", "better", ",", "because", "of", "the", "side", "of", "a", "line", "they", "are", "born", "on", ",", "that", "are", "at", "fault"]]}]